[
  {
    "id": "NANAB1----",
    "name": "Naturbruk",
    "programUrl": "https://www.udir.no/kl06/NANAB1----",
    "lareplanUrl": "https://data.udir.no/kl06/NAB1-01",
    "kompetansemaal": [
      {
        "rekkefoelge": 1,
        "tilhoerer-hovedomraade": null,
        "kode": "K8096",
        "uri": "http://psi.udir.no/kl06/K8096",
        "url-data": "http://data.udir.no/kl06/K8096",
        "tittel": "utføre arbeidsoppgaver knyttet til stell av planter basert på kunnskaper om planters miljøkrav"
      },
      {
        "rekkefoelge": 2,
        "tilhoerer-hovedomraade": null,
        "kode": "K8097",
        "uri": "http://psi.udir.no/kl06/K8097",
        "url-data": "http://data.udir.no/kl06/K8097",
        "tittel": "utføre arbeidsoppgaver knyttet til stell av dyr eller fisk basert på etiske retningslinjer og kunnskaper om organismenes miljøkrav"
      },
      {
        "rekkefoelge": 3,
        "tilhoerer-hovedomraade": null,
        "kode": "K8098",
        "uri": "http://psi.udir.no/kl06/K8098",
        "url-data": "http://data.udir.no/kl06/K8098",
        "tittel": "utføre arbeidsoppgaver innen produksjon og høsting eller fangst"
      },
      {
        "rekkefoelge": 4,
        "tilhoerer-hovedomraade": null,
        "kode": "K8099",
        "uri": "http://psi.udir.no/kl06/K8099",
        "url-data": "http://data.udir.no/kl06/K8099",
        "tittel": "utføre enkel bearbeiding av råstoff"
      },
      {
        "rekkefoelge": 5,
        "tilhoerer-hovedomraade": null,
        "kode": "K8100",
        "uri": "http://psi.udir.no/kl06/K8100",
        "url-data": "http://data.udir.no/kl06/K8100",
        "tittel": "beskrive og presentere et produkt rettet mot en aktuell målgruppe"
      },
      {
        "rekkefoelge": 6,
        "tilhoerer-hovedomraade": null,
        "kode": "K8101",
        "uri": "http://psi.udir.no/kl06/K8101",
        "url-data": "http://data.udir.no/kl06/K8101",
        "tittel": "identifisere, klassifisere og presentere et utvalg arter og materialer"
      },
      {
        "rekkefoelge": 7,
        "tilhoerer-hovedomraade": null,
        "kode": "K8102",
        "uri": "http://psi.udir.no/kl06/K8102",
        "url-data": "http://data.udir.no/kl06/K8102",
        "tittel": "foreta enkle beregninger av råvare- og materialforbruk, og kunne beregne utbyttet i produksjonsprosessen"
      },
      {
        "rekkefoelge": 8,
        "tilhoerer-hovedomraade": null,
        "kode": "K8103",
        "uri": "http://psi.udir.no/kl06/K8103",
        "url-data": "http://data.udir.no/kl06/K8103",
        "tittel": "velge og bruke riktig redskap, utstyr og instrumenter i tilknytning til produksjonen"
      },
      {
        "rekkefoelge": 9,
        "tilhoerer-hovedomraade": null,
        "kode": "K8104",
        "uri": "http://psi.udir.no/kl06/K8104",
        "url-data": "http://data.udir.no/kl06/K8104",
        "tittel": "foreta enkelt ettersyn av aktuelle framkomstmidler, motorer, redskaper, utstyr og instrumenter"
      },
      {
        "rekkefoelge": 10,
        "tilhoerer-hovedomraade": null,
        "kode": "K8105",
        "uri": "http://psi.udir.no/kl06/K8105",
        "url-data": "http://data.udir.no/kl06/K8105",
        "tittel": "følge bruksanvisning og bruke manual for utstyr som benyttes i produksjonen"
      },
      {
        "rekkefoelge": 11,
        "tilhoerer-hovedomraade": null,
        "kode": "K8106",
        "uri": "http://psi.udir.no/kl06/K8106",
        "url-data": "http://data.udir.no/kl06/K8106",
        "tittel": "velge og bruke materialer ut fra arbeidsoppdrag og materialets egenskaper"
      },
      {
        "rekkefoelge": 12,
        "tilhoerer-hovedomraade": null,
        "kode": "K8107",
        "uri": "http://psi.udir.no/kl06/K8107",
        "url-data": "http://data.udir.no/kl06/K8107",
        "tittel": "utføre enkelt vedlikehold på bygninger og installasjoner som benyttes i produksjonen"
      },
      {
        "rekkefoelge": 13,
        "tilhoerer-hovedomraade": null,
        "kode": "K8108",
        "uri": "http://psi.udir.no/kl06/K8108",
        "url-data": "http://data.udir.no/kl06/K8108",
        "tittel": "planlegge og gjennomføre arbeid og aktiviteter i tråd med gjeldende yrkesmessige krav til utførelse, helse, miljø og sikkerhet og kvalitetssystemer"
      },
      {
        "rekkefoelge": 14,
        "tilhoerer-hovedomraade": null,
        "kode": "K8109",
        "uri": "http://psi.udir.no/kl06/K8109",
        "url-data": "http://data.udir.no/kl06/K8109",
        "tittel": "bruke riktig arbeidsteknikk, verne- og sikkerhetsutstyr og velge hensiktsmessig påkledning for arbeid og aktiviteter under ulike forhold"
      },
      {
        "rekkefoelge": 15,
        "tilhoerer-hovedomraade": null,
        "kode": "K8110",
        "uri": "http://psi.udir.no/kl06/K8110",
        "url-data": "http://data.udir.no/kl06/K8110",
        "tittel": "utøve brannvern og førstehjelp i tråd med gjeldende krav"
      },
      {
        "rekkefoelge": 16,
        "tilhoerer-hovedomraade": null,
        "kode": "K8111",
        "uri": "http://psi.udir.no/kl06/K8111",
        "url-data": "http://data.udir.no/kl06/K8111",
        "tittel": "dokumentere gjennomført opplæring i forhold til IMO 60 (gjelder kun for elever som har fiske og fangst som en av produksjonene)"
      }
    ]
  },
  {
    "id": "NANAB1----",
    "name": "Naturbruk",
    "programUrl": "https://www.udir.no/kl06/NANAB1----",
    "lareplanUrl": "https://data.udir.no/kl06/NAB1-01",
    "kompetansemaal": [
      {
        "rekkefoelge": 1,
        "tilhoerer-hovedomraade": null,
        "kode": "K8096",
        "uri": "http://psi.udir.no/kl06/K8096",
        "url-data": "http://data.udir.no/kl06/K8096",
        "tittel": "utføre arbeidsoppgaver knyttet til stell av planter basert på kunnskaper om planters miljøkrav"
      },
      {
        "rekkefoelge": 2,
        "tilhoerer-hovedomraade": null,
        "kode": "K8097",
        "uri": "http://psi.udir.no/kl06/K8097",
        "url-data": "http://data.udir.no/kl06/K8097",
        "tittel": "utføre arbeidsoppgaver knyttet til stell av dyr eller fisk basert på etiske retningslinjer og kunnskaper om organismenes miljøkrav"
      },
      {
        "rekkefoelge": 3,
        "tilhoerer-hovedomraade": null,
        "kode": "K8098",
        "uri": "http://psi.udir.no/kl06/K8098",
        "url-data": "http://data.udir.no/kl06/K8098",
        "tittel": "utføre arbeidsoppgaver innen produksjon og høsting eller fangst"
      },
      {
        "rekkefoelge": 4,
        "tilhoerer-hovedomraade": null,
        "kode": "K8099",
        "uri": "http://psi.udir.no/kl06/K8099",
        "url-data": "http://data.udir.no/kl06/K8099",
        "tittel": "utføre enkel bearbeiding av råstoff"
      },
      {
        "rekkefoelge": 5,
        "tilhoerer-hovedomraade": null,
        "kode": "K8100",
        "uri": "http://psi.udir.no/kl06/K8100",
        "url-data": "http://data.udir.no/kl06/K8100",
        "tittel": "beskrive og presentere et produkt rettet mot en aktuell målgruppe"
      },
      {
        "rekkefoelge": 6,
        "tilhoerer-hovedomraade": null,
        "kode": "K8101",
        "uri": "http://psi.udir.no/kl06/K8101",
        "url-data": "http://data.udir.no/kl06/K8101",
        "tittel": "identifisere, klassifisere og presentere et utvalg arter og materialer"
      },
      {
        "rekkefoelge": 7,
        "tilhoerer-hovedomraade": null,
        "kode": "K8102",
        "uri": "http://psi.udir.no/kl06/K8102",
        "url-data": "http://data.udir.no/kl06/K8102",
        "tittel": "foreta enkle beregninger av råvare- og materialforbruk, og kunne beregne utbyttet i produksjonsprosessen"
      },
      {
        "rekkefoelge": 8,
        "tilhoerer-hovedomraade": null,
        "kode": "K8103",
        "uri": "http://psi.udir.no/kl06/K8103",
        "url-data": "http://data.udir.no/kl06/K8103",
        "tittel": "velge og bruke riktig redskap, utstyr og instrumenter i tilknytning til produksjonen"
      },
      {
        "rekkefoelge": 9,
        "tilhoerer-hovedomraade": null,
        "kode": "K8104",
        "uri": "http://psi.udir.no/kl06/K8104",
        "url-data": "http://data.udir.no/kl06/K8104",
        "tittel": "foreta enkelt ettersyn av aktuelle framkomstmidler, motorer, redskaper, utstyr og instrumenter"
      },
      {
        "rekkefoelge": 10,
        "tilhoerer-hovedomraade": null,
        "kode": "K8105",
        "uri": "http://psi.udir.no/kl06/K8105",
        "url-data": "http://data.udir.no/kl06/K8105",
        "tittel": "følge bruksanvisning og bruke manual for utstyr som benyttes i produksjonen"
      },
      {
        "rekkefoelge": 11,
        "tilhoerer-hovedomraade": null,
        "kode": "K8106",
        "uri": "http://psi.udir.no/kl06/K8106",
        "url-data": "http://data.udir.no/kl06/K8106",
        "tittel": "velge og bruke materialer ut fra arbeidsoppdrag og materialets egenskaper"
      },
      {
        "rekkefoelge": 12,
        "tilhoerer-hovedomraade": null,
        "kode": "K8107",
        "uri": "http://psi.udir.no/kl06/K8107",
        "url-data": "http://data.udir.no/kl06/K8107",
        "tittel": "utføre enkelt vedlikehold på bygninger og installasjoner som benyttes i produksjonen"
      },
      {
        "rekkefoelge": 13,
        "tilhoerer-hovedomraade": null,
        "kode": "K8108",
        "uri": "http://psi.udir.no/kl06/K8108",
        "url-data": "http://data.udir.no/kl06/K8108",
        "tittel": "planlegge og gjennomføre arbeid og aktiviteter i tråd med gjeldende yrkesmessige krav til utførelse, helse, miljø og sikkerhet og kvalitetssystemer"
      },
      {
        "rekkefoelge": 14,
        "tilhoerer-hovedomraade": null,
        "kode": "K8109",
        "uri": "http://psi.udir.no/kl06/K8109",
        "url-data": "http://data.udir.no/kl06/K8109",
        "tittel": "bruke riktig arbeidsteknikk, verne- og sikkerhetsutstyr og velge hensiktsmessig påkledning for arbeid og aktiviteter under ulike forhold"
      },
      {
        "rekkefoelge": 15,
        "tilhoerer-hovedomraade": null,
        "kode": "K8110",
        "uri": "http://psi.udir.no/kl06/K8110",
        "url-data": "http://data.udir.no/kl06/K8110",
        "tittel": "utøve brannvern og førstehjelp i tråd med gjeldende krav"
      },
      {
        "rekkefoelge": 16,
        "tilhoerer-hovedomraade": null,
        "kode": "K8111",
        "uri": "http://psi.udir.no/kl06/K8111",
        "url-data": "http://data.udir.no/kl06/K8111",
        "tittel": "dokumentere gjennomført opplæring i forhold til IMO 60 (gjelder kun for elever som har fiske og fangst som en av produksjonene)"
      }
    ]
  },
  {
    "id": "NANAB1----",
    "name": "Naturbruk",
    "programUrl": "https://www.udir.no/kl06/NANAB1----",
    "lareplanUrl": "https://data.udir.no/kl06/NAB1-01",
    "kompetansemaal": [
      {
        "rekkefoelge": 1,
        "tilhoerer-hovedomraade": null,
        "kode": "K8096",
        "uri": "http://psi.udir.no/kl06/K8096",
        "url-data": "http://data.udir.no/kl06/K8096",
        "tittel": "utføre arbeidsoppgaver knyttet til stell av planter basert på kunnskaper om planters miljøkrav"
      },
      {
        "rekkefoelge": 2,
        "tilhoerer-hovedomraade": null,
        "kode": "K8097",
        "uri": "http://psi.udir.no/kl06/K8097",
        "url-data": "http://data.udir.no/kl06/K8097",
        "tittel": "utføre arbeidsoppgaver knyttet til stell av dyr eller fisk basert på etiske retningslinjer og kunnskaper om organismenes miljøkrav"
      },
      {
        "rekkefoelge": 3,
        "tilhoerer-hovedomraade": null,
        "kode": "K8098",
        "uri": "http://psi.udir.no/kl06/K8098",
        "url-data": "http://data.udir.no/kl06/K8098",
        "tittel": "utføre arbeidsoppgaver innen produksjon og høsting eller fangst"
      },
      {
        "rekkefoelge": 4,
        "tilhoerer-hovedomraade": null,
        "kode": "K8099",
        "uri": "http://psi.udir.no/kl06/K8099",
        "url-data": "http://data.udir.no/kl06/K8099",
        "tittel": "utføre enkel bearbeiding av råstoff"
      },
      {
        "rekkefoelge": 5,
        "tilhoerer-hovedomraade": null,
        "kode": "K8100",
        "uri": "http://psi.udir.no/kl06/K8100",
        "url-data": "http://data.udir.no/kl06/K8100",
        "tittel": "beskrive og presentere et produkt rettet mot en aktuell målgruppe"
      },
      {
        "rekkefoelge": 6,
        "tilhoerer-hovedomraade": null,
        "kode": "K8101",
        "uri": "http://psi.udir.no/kl06/K8101",
        "url-data": "http://data.udir.no/kl06/K8101",
        "tittel": "identifisere, klassifisere og presentere et utvalg arter og materialer"
      },
      {
        "rekkefoelge": 7,
        "tilhoerer-hovedomraade": null,
        "kode": "K8102",
        "uri": "http://psi.udir.no/kl06/K8102",
        "url-data": "http://data.udir.no/kl06/K8102",
        "tittel": "foreta enkle beregninger av råvare- og materialforbruk, og kunne beregne utbyttet i produksjonsprosessen"
      },
      {
        "rekkefoelge": 8,
        "tilhoerer-hovedomraade": null,
        "kode": "K8103",
        "uri": "http://psi.udir.no/kl06/K8103",
        "url-data": "http://data.udir.no/kl06/K8103",
        "tittel": "velge og bruke riktig redskap, utstyr og instrumenter i tilknytning til produksjonen"
      },
      {
        "rekkefoelge": 9,
        "tilhoerer-hovedomraade": null,
        "kode": "K8104",
        "uri": "http://psi.udir.no/kl06/K8104",
        "url-data": "http://data.udir.no/kl06/K8104",
        "tittel": "foreta enkelt ettersyn av aktuelle framkomstmidler, motorer, redskaper, utstyr og instrumenter"
      },
      {
        "rekkefoelge": 10,
        "tilhoerer-hovedomraade": null,
        "kode": "K8105",
        "uri": "http://psi.udir.no/kl06/K8105",
        "url-data": "http://data.udir.no/kl06/K8105",
        "tittel": "følge bruksanvisning og bruke manual for utstyr som benyttes i produksjonen"
      },
      {
        "rekkefoelge": 11,
        "tilhoerer-hovedomraade": null,
        "kode": "K8106",
        "uri": "http://psi.udir.no/kl06/K8106",
        "url-data": "http://data.udir.no/kl06/K8106",
        "tittel": "velge og bruke materialer ut fra arbeidsoppdrag og materialets egenskaper"
      },
      {
        "rekkefoelge": 12,
        "tilhoerer-hovedomraade": null,
        "kode": "K8107",
        "uri": "http://psi.udir.no/kl06/K8107",
        "url-data": "http://data.udir.no/kl06/K8107",
        "tittel": "utføre enkelt vedlikehold på bygninger og installasjoner som benyttes i produksjonen"
      },
      {
        "rekkefoelge": 13,
        "tilhoerer-hovedomraade": null,
        "kode": "K8108",
        "uri": "http://psi.udir.no/kl06/K8108",
        "url-data": "http://data.udir.no/kl06/K8108",
        "tittel": "planlegge og gjennomføre arbeid og aktiviteter i tråd med gjeldende yrkesmessige krav til utførelse, helse, miljø og sikkerhet og kvalitetssystemer"
      },
      {
        "rekkefoelge": 14,
        "tilhoerer-hovedomraade": null,
        "kode": "K8109",
        "uri": "http://psi.udir.no/kl06/K8109",
        "url-data": "http://data.udir.no/kl06/K8109",
        "tittel": "bruke riktig arbeidsteknikk, verne- og sikkerhetsutstyr og velge hensiktsmessig påkledning for arbeid og aktiviteter under ulike forhold"
      },
      {
        "rekkefoelge": 15,
        "tilhoerer-hovedomraade": null,
        "kode": "K8110",
        "uri": "http://psi.udir.no/kl06/K8110",
        "url-data": "http://data.udir.no/kl06/K8110",
        "tittel": "utøve brannvern og førstehjelp i tråd med gjeldende krav"
      },
      {
        "rekkefoelge": 16,
        "tilhoerer-hovedomraade": null,
        "kode": "K8111",
        "uri": "http://psi.udir.no/kl06/K8111",
        "url-data": "http://data.udir.no/kl06/K8111",
        "tittel": "dokumentere gjennomført opplæring i forhold til IMO 60 (gjelder kun for elever som har fiske og fangst som en av produksjonene)"
      }
    ]
  },
  {
    "id": "NANAB1----",
    "name": "Naturbruk",
    "programUrl": "https://www.udir.no/kl06/NANAB1----",
    "lareplanUrl": "https://data.udir.no/kl06/NAB1-01",
    "kompetansemaal": [
      {
        "rekkefoelge": 1,
        "tilhoerer-hovedomraade": null,
        "kode": "K8096",
        "uri": "http://psi.udir.no/kl06/K8096",
        "url-data": "http://data.udir.no/kl06/K8096",
        "tittel": "utføre arbeidsoppgaver knyttet til stell av planter basert på kunnskaper om planters miljøkrav"
      },
      {
        "rekkefoelge": 2,
        "tilhoerer-hovedomraade": null,
        "kode": "K8097",
        "uri": "http://psi.udir.no/kl06/K8097",
        "url-data": "http://data.udir.no/kl06/K8097",
        "tittel": "utføre arbeidsoppgaver knyttet til stell av dyr eller fisk basert på etiske retningslinjer og kunnskaper om organismenes miljøkrav"
      },
      {
        "rekkefoelge": 3,
        "tilhoerer-hovedomraade": null,
        "kode": "K8098",
        "uri": "http://psi.udir.no/kl06/K8098",
        "url-data": "http://data.udir.no/kl06/K8098",
        "tittel": "utføre arbeidsoppgaver innen produksjon og høsting eller fangst"
      },
      {
        "rekkefoelge": 4,
        "tilhoerer-hovedomraade": null,
        "kode": "K8099",
        "uri": "http://psi.udir.no/kl06/K8099",
        "url-data": "http://data.udir.no/kl06/K8099",
        "tittel": "utføre enkel bearbeiding av råstoff"
      },
      {
        "rekkefoelge": 5,
        "tilhoerer-hovedomraade": null,
        "kode": "K8100",
        "uri": "http://psi.udir.no/kl06/K8100",
        "url-data": "http://data.udir.no/kl06/K8100",
        "tittel": "beskrive og presentere et produkt rettet mot en aktuell målgruppe"
      },
      {
        "rekkefoelge": 6,
        "tilhoerer-hovedomraade": null,
        "kode": "K8101",
        "uri": "http://psi.udir.no/kl06/K8101",
        "url-data": "http://data.udir.no/kl06/K8101",
        "tittel": "identifisere, klassifisere og presentere et utvalg arter og materialer"
      },
      {
        "rekkefoelge": 7,
        "tilhoerer-hovedomraade": null,
        "kode": "K8102",
        "uri": "http://psi.udir.no/kl06/K8102",
        "url-data": "http://data.udir.no/kl06/K8102",
        "tittel": "foreta enkle beregninger av råvare- og materialforbruk, og kunne beregne utbyttet i produksjonsprosessen"
      },
      {
        "rekkefoelge": 8,
        "tilhoerer-hovedomraade": null,
        "kode": "K8103",
        "uri": "http://psi.udir.no/kl06/K8103",
        "url-data": "http://data.udir.no/kl06/K8103",
        "tittel": "velge og bruke riktig redskap, utstyr og instrumenter i tilknytning til produksjonen"
      },
      {
        "rekkefoelge": 9,
        "tilhoerer-hovedomraade": null,
        "kode": "K8104",
        "uri": "http://psi.udir.no/kl06/K8104",
        "url-data": "http://data.udir.no/kl06/K8104",
        "tittel": "foreta enkelt ettersyn av aktuelle framkomstmidler, motorer, redskaper, utstyr og instrumenter"
      },
      {
        "rekkefoelge": 10,
        "tilhoerer-hovedomraade": null,
        "kode": "K8105",
        "uri": "http://psi.udir.no/kl06/K8105",
        "url-data": "http://data.udir.no/kl06/K8105",
        "tittel": "følge bruksanvisning og bruke manual for utstyr som benyttes i produksjonen"
      },
      {
        "rekkefoelge": 11,
        "tilhoerer-hovedomraade": null,
        "kode": "K8106",
        "uri": "http://psi.udir.no/kl06/K8106",
        "url-data": "http://data.udir.no/kl06/K8106",
        "tittel": "velge og bruke materialer ut fra arbeidsoppdrag og materialets egenskaper"
      },
      {
        "rekkefoelge": 12,
        "tilhoerer-hovedomraade": null,
        "kode": "K8107",
        "uri": "http://psi.udir.no/kl06/K8107",
        "url-data": "http://data.udir.no/kl06/K8107",
        "tittel": "utføre enkelt vedlikehold på bygninger og installasjoner som benyttes i produksjonen"
      },
      {
        "rekkefoelge": 13,
        "tilhoerer-hovedomraade": null,
        "kode": "K8108",
        "uri": "http://psi.udir.no/kl06/K8108",
        "url-data": "http://data.udir.no/kl06/K8108",
        "tittel": "planlegge og gjennomføre arbeid og aktiviteter i tråd med gjeldende yrkesmessige krav til utførelse, helse, miljø og sikkerhet og kvalitetssystemer"
      },
      {
        "rekkefoelge": 14,
        "tilhoerer-hovedomraade": null,
        "kode": "K8109",
        "uri": "http://psi.udir.no/kl06/K8109",
        "url-data": "http://data.udir.no/kl06/K8109",
        "tittel": "bruke riktig arbeidsteknikk, verne- og sikkerhetsutstyr og velge hensiktsmessig påkledning for arbeid og aktiviteter under ulike forhold"
      },
      {
        "rekkefoelge": 15,
        "tilhoerer-hovedomraade": null,
        "kode": "K8110",
        "uri": "http://psi.udir.no/kl06/K8110",
        "url-data": "http://data.udir.no/kl06/K8110",
        "tittel": "utøve brannvern og førstehjelp i tråd med gjeldende krav"
      },
      {
        "rekkefoelge": 16,
        "tilhoerer-hovedomraade": null,
        "kode": "K8111",
        "uri": "http://psi.udir.no/kl06/K8111",
        "url-data": "http://data.udir.no/kl06/K8111",
        "tittel": "dokumentere gjennomført opplæring i forhold til IMO 60 (gjelder kun for elever som har fiske og fangst som en av produksjonene)"
      }
    ]
  },
  {
    "id": "NANAB1----",
    "name": "Naturbruk",
    "programUrl": "https://www.udir.no/kl06/NANAB1----",
    "lareplanUrl": "https://data.udir.no/kl06/NAB1-01",
    "kompetansemaal": [
      {
        "rekkefoelge": 1,
        "tilhoerer-hovedomraade": null,
        "kode": "K8096",
        "uri": "http://psi.udir.no/kl06/K8096",
        "url-data": "http://data.udir.no/kl06/K8096",
        "tittel": "utføre arbeidsoppgaver knyttet til stell av planter basert på kunnskaper om planters miljøkrav"
      },
      {
        "rekkefoelge": 2,
        "tilhoerer-hovedomraade": null,
        "kode": "K8097",
        "uri": "http://psi.udir.no/kl06/K8097",
        "url-data": "http://data.udir.no/kl06/K8097",
        "tittel": "utføre arbeidsoppgaver knyttet til stell av dyr eller fisk basert på etiske retningslinjer og kunnskaper om organismenes miljøkrav"
      },
      {
        "rekkefoelge": 3,
        "tilhoerer-hovedomraade": null,
        "kode": "K8098",
        "uri": "http://psi.udir.no/kl06/K8098",
        "url-data": "http://data.udir.no/kl06/K8098",
        "tittel": "utføre arbeidsoppgaver innen produksjon og høsting eller fangst"
      },
      {
        "rekkefoelge": 4,
        "tilhoerer-hovedomraade": null,
        "kode": "K8099",
        "uri": "http://psi.udir.no/kl06/K8099",
        "url-data": "http://data.udir.no/kl06/K8099",
        "tittel": "utføre enkel bearbeiding av råstoff"
      },
      {
        "rekkefoelge": 5,
        "tilhoerer-hovedomraade": null,
        "kode": "K8100",
        "uri": "http://psi.udir.no/kl06/K8100",
        "url-data": "http://data.udir.no/kl06/K8100",
        "tittel": "beskrive og presentere et produkt rettet mot en aktuell målgruppe"
      },
      {
        "rekkefoelge": 6,
        "tilhoerer-hovedomraade": null,
        "kode": "K8101",
        "uri": "http://psi.udir.no/kl06/K8101",
        "url-data": "http://data.udir.no/kl06/K8101",
        "tittel": "identifisere, klassifisere og presentere et utvalg arter og materialer"
      },
      {
        "rekkefoelge": 7,
        "tilhoerer-hovedomraade": null,
        "kode": "K8102",
        "uri": "http://psi.udir.no/kl06/K8102",
        "url-data": "http://data.udir.no/kl06/K8102",
        "tittel": "foreta enkle beregninger av råvare- og materialforbruk, og kunne beregne utbyttet i produksjonsprosessen"
      },
      {
        "rekkefoelge": 8,
        "tilhoerer-hovedomraade": null,
        "kode": "K8103",
        "uri": "http://psi.udir.no/kl06/K8103",
        "url-data": "http://data.udir.no/kl06/K8103",
        "tittel": "velge og bruke riktig redskap, utstyr og instrumenter i tilknytning til produksjonen"
      },
      {
        "rekkefoelge": 9,
        "tilhoerer-hovedomraade": null,
        "kode": "K8104",
        "uri": "http://psi.udir.no/kl06/K8104",
        "url-data": "http://data.udir.no/kl06/K8104",
        "tittel": "foreta enkelt ettersyn av aktuelle framkomstmidler, motorer, redskaper, utstyr og instrumenter"
      },
      {
        "rekkefoelge": 10,
        "tilhoerer-hovedomraade": null,
        "kode": "K8105",
        "uri": "http://psi.udir.no/kl06/K8105",
        "url-data": "http://data.udir.no/kl06/K8105",
        "tittel": "følge bruksanvisning og bruke manual for utstyr som benyttes i produksjonen"
      },
      {
        "rekkefoelge": 11,
        "tilhoerer-hovedomraade": null,
        "kode": "K8106",
        "uri": "http://psi.udir.no/kl06/K8106",
        "url-data": "http://data.udir.no/kl06/K8106",
        "tittel": "velge og bruke materialer ut fra arbeidsoppdrag og materialets egenskaper"
      },
      {
        "rekkefoelge": 12,
        "tilhoerer-hovedomraade": null,
        "kode": "K8107",
        "uri": "http://psi.udir.no/kl06/K8107",
        "url-data": "http://data.udir.no/kl06/K8107",
        "tittel": "utføre enkelt vedlikehold på bygninger og installasjoner som benyttes i produksjonen"
      },
      {
        "rekkefoelge": 13,
        "tilhoerer-hovedomraade": null,
        "kode": "K8108",
        "uri": "http://psi.udir.no/kl06/K8108",
        "url-data": "http://data.udir.no/kl06/K8108",
        "tittel": "planlegge og gjennomføre arbeid og aktiviteter i tråd med gjeldende yrkesmessige krav til utførelse, helse, miljø og sikkerhet og kvalitetssystemer"
      },
      {
        "rekkefoelge": 14,
        "tilhoerer-hovedomraade": null,
        "kode": "K8109",
        "uri": "http://psi.udir.no/kl06/K8109",
        "url-data": "http://data.udir.no/kl06/K8109",
        "tittel": "bruke riktig arbeidsteknikk, verne- og sikkerhetsutstyr og velge hensiktsmessig påkledning for arbeid og aktiviteter under ulike forhold"
      },
      {
        "rekkefoelge": 15,
        "tilhoerer-hovedomraade": null,
        "kode": "K8110",
        "uri": "http://psi.udir.no/kl06/K8110",
        "url-data": "http://data.udir.no/kl06/K8110",
        "tittel": "utøve brannvern og førstehjelp i tråd med gjeldende krav"
      },
      {
        "rekkefoelge": 16,
        "tilhoerer-hovedomraade": null,
        "kode": "K8111",
        "uri": "http://psi.udir.no/kl06/K8111",
        "url-data": "http://data.udir.no/kl06/K8111",
        "tittel": "dokumentere gjennomført opplæring i forhold til IMO 60 (gjelder kun for elever som har fiske og fangst som en av produksjonene)"
      }
    ]
  },
  {
    "id": "NANAB1----",
    "name": "Naturbruk",
    "programUrl": "https://www.udir.no/kl06/NANAB1----",
    "lareplanUrl": "https://data.udir.no/kl06/NAB1-01",
    "kompetansemaal": [
      {
        "rekkefoelge": 1,
        "tilhoerer-hovedomraade": null,
        "kode": "K8096",
        "uri": "http://psi.udir.no/kl06/K8096",
        "url-data": "http://data.udir.no/kl06/K8096",
        "tittel": "utføre arbeidsoppgaver knyttet til stell av planter basert på kunnskaper om planters miljøkrav"
      },
      {
        "rekkefoelge": 2,
        "tilhoerer-hovedomraade": null,
        "kode": "K8097",
        "uri": "http://psi.udir.no/kl06/K8097",
        "url-data": "http://data.udir.no/kl06/K8097",
        "tittel": "utføre arbeidsoppgaver knyttet til stell av dyr eller fisk basert på etiske retningslinjer og kunnskaper om organismenes miljøkrav"
      },
      {
        "rekkefoelge": 3,
        "tilhoerer-hovedomraade": null,
        "kode": "K8098",
        "uri": "http://psi.udir.no/kl06/K8098",
        "url-data": "http://data.udir.no/kl06/K8098",
        "tittel": "utføre arbeidsoppgaver innen produksjon og høsting eller fangst"
      },
      {
        "rekkefoelge": 4,
        "tilhoerer-hovedomraade": null,
        "kode": "K8099",
        "uri": "http://psi.udir.no/kl06/K8099",
        "url-data": "http://data.udir.no/kl06/K8099",
        "tittel": "utføre enkel bearbeiding av råstoff"
      },
      {
        "rekkefoelge": 5,
        "tilhoerer-hovedomraade": null,
        "kode": "K8100",
        "uri": "http://psi.udir.no/kl06/K8100",
        "url-data": "http://data.udir.no/kl06/K8100",
        "tittel": "beskrive og presentere et produkt rettet mot en aktuell målgruppe"
      },
      {
        "rekkefoelge": 6,
        "tilhoerer-hovedomraade": null,
        "kode": "K8101",
        "uri": "http://psi.udir.no/kl06/K8101",
        "url-data": "http://data.udir.no/kl06/K8101",
        "tittel": "identifisere, klassifisere og presentere et utvalg arter og materialer"
      },
      {
        "rekkefoelge": 7,
        "tilhoerer-hovedomraade": null,
        "kode": "K8102",
        "uri": "http://psi.udir.no/kl06/K8102",
        "url-data": "http://data.udir.no/kl06/K8102",
        "tittel": "foreta enkle beregninger av råvare- og materialforbruk, og kunne beregne utbyttet i produksjonsprosessen"
      },
      {
        "rekkefoelge": 8,
        "tilhoerer-hovedomraade": null,
        "kode": "K8103",
        "uri": "http://psi.udir.no/kl06/K8103",
        "url-data": "http://data.udir.no/kl06/K8103",
        "tittel": "velge og bruke riktig redskap, utstyr og instrumenter i tilknytning til produksjonen"
      },
      {
        "rekkefoelge": 9,
        "tilhoerer-hovedomraade": null,
        "kode": "K8104",
        "uri": "http://psi.udir.no/kl06/K8104",
        "url-data": "http://data.udir.no/kl06/K8104",
        "tittel": "foreta enkelt ettersyn av aktuelle framkomstmidler, motorer, redskaper, utstyr og instrumenter"
      },
      {
        "rekkefoelge": 10,
        "tilhoerer-hovedomraade": null,
        "kode": "K8105",
        "uri": "http://psi.udir.no/kl06/K8105",
        "url-data": "http://data.udir.no/kl06/K8105",
        "tittel": "følge bruksanvisning og bruke manual for utstyr som benyttes i produksjonen"
      },
      {
        "rekkefoelge": 11,
        "tilhoerer-hovedomraade": null,
        "kode": "K8106",
        "uri": "http://psi.udir.no/kl06/K8106",
        "url-data": "http://data.udir.no/kl06/K8106",
        "tittel": "velge og bruke materialer ut fra arbeidsoppdrag og materialets egenskaper"
      },
      {
        "rekkefoelge": 12,
        "tilhoerer-hovedomraade": null,
        "kode": "K8107",
        "uri": "http://psi.udir.no/kl06/K8107",
        "url-data": "http://data.udir.no/kl06/K8107",
        "tittel": "utføre enkelt vedlikehold på bygninger og installasjoner som benyttes i produksjonen"
      },
      {
        "rekkefoelge": 13,
        "tilhoerer-hovedomraade": null,
        "kode": "K8108",
        "uri": "http://psi.udir.no/kl06/K8108",
        "url-data": "http://data.udir.no/kl06/K8108",
        "tittel": "planlegge og gjennomføre arbeid og aktiviteter i tråd med gjeldende yrkesmessige krav til utførelse, helse, miljø og sikkerhet og kvalitetssystemer"
      },
      {
        "rekkefoelge": 14,
        "tilhoerer-hovedomraade": null,
        "kode": "K8109",
        "uri": "http://psi.udir.no/kl06/K8109",
        "url-data": "http://data.udir.no/kl06/K8109",
        "tittel": "bruke riktig arbeidsteknikk, verne- og sikkerhetsutstyr og velge hensiktsmessig påkledning for arbeid og aktiviteter under ulike forhold"
      },
      {
        "rekkefoelge": 15,
        "tilhoerer-hovedomraade": null,
        "kode": "K8110",
        "uri": "http://psi.udir.no/kl06/K8110",
        "url-data": "http://data.udir.no/kl06/K8110",
        "tittel": "utøve brannvern og førstehjelp i tråd med gjeldende krav"
      },
      {
        "rekkefoelge": 16,
        "tilhoerer-hovedomraade": null,
        "kode": "K8111",
        "uri": "http://psi.udir.no/kl06/K8111",
        "url-data": "http://data.udir.no/kl06/K8111",
        "tittel": "dokumentere gjennomført opplæring i forhold til IMO 60 (gjelder kun for elever som har fiske og fangst som en av produksjonene)"
      }
    ]
  },
  {
    "id": "NANAB1----",
    "name": "Naturbruk",
    "programUrl": "https://www.udir.no/kl06/NANAB1----",
    "lareplanUrl": "https://data.udir.no/kl06/NAB1-01",
    "kompetansemaal": [
      {
        "rekkefoelge": 1,
        "tilhoerer-hovedomraade": null,
        "kode": "K8096",
        "uri": "http://psi.udir.no/kl06/K8096",
        "url-data": "http://data.udir.no/kl06/K8096",
        "tittel": "utføre arbeidsoppgaver knyttet til stell av planter basert på kunnskaper om planters miljøkrav"
      },
      {
        "rekkefoelge": 2,
        "tilhoerer-hovedomraade": null,
        "kode": "K8097",
        "uri": "http://psi.udir.no/kl06/K8097",
        "url-data": "http://data.udir.no/kl06/K8097",
        "tittel": "utføre arbeidsoppgaver knyttet til stell av dyr eller fisk basert på etiske retningslinjer og kunnskaper om organismenes miljøkrav"
      },
      {
        "rekkefoelge": 3,
        "tilhoerer-hovedomraade": null,
        "kode": "K8098",
        "uri": "http://psi.udir.no/kl06/K8098",
        "url-data": "http://data.udir.no/kl06/K8098",
        "tittel": "utføre arbeidsoppgaver innen produksjon og høsting eller fangst"
      },
      {
        "rekkefoelge": 4,
        "tilhoerer-hovedomraade": null,
        "kode": "K8099",
        "uri": "http://psi.udir.no/kl06/K8099",
        "url-data": "http://data.udir.no/kl06/K8099",
        "tittel": "utføre enkel bearbeiding av råstoff"
      },
      {
        "rekkefoelge": 5,
        "tilhoerer-hovedomraade": null,
        "kode": "K8100",
        "uri": "http://psi.udir.no/kl06/K8100",
        "url-data": "http://data.udir.no/kl06/K8100",
        "tittel": "beskrive og presentere et produkt rettet mot en aktuell målgruppe"
      },
      {
        "rekkefoelge": 6,
        "tilhoerer-hovedomraade": null,
        "kode": "K8101",
        "uri": "http://psi.udir.no/kl06/K8101",
        "url-data": "http://data.udir.no/kl06/K8101",
        "tittel": "identifisere, klassifisere og presentere et utvalg arter og materialer"
      },
      {
        "rekkefoelge": 7,
        "tilhoerer-hovedomraade": null,
        "kode": "K8102",
        "uri": "http://psi.udir.no/kl06/K8102",
        "url-data": "http://data.udir.no/kl06/K8102",
        "tittel": "foreta enkle beregninger av råvare- og materialforbruk, og kunne beregne utbyttet i produksjonsprosessen"
      },
      {
        "rekkefoelge": 8,
        "tilhoerer-hovedomraade": null,
        "kode": "K8103",
        "uri": "http://psi.udir.no/kl06/K8103",
        "url-data": "http://data.udir.no/kl06/K8103",
        "tittel": "velge og bruke riktig redskap, utstyr og instrumenter i tilknytning til produksjonen"
      },
      {
        "rekkefoelge": 9,
        "tilhoerer-hovedomraade": null,
        "kode": "K8104",
        "uri": "http://psi.udir.no/kl06/K8104",
        "url-data": "http://data.udir.no/kl06/K8104",
        "tittel": "foreta enkelt ettersyn av aktuelle framkomstmidler, motorer, redskaper, utstyr og instrumenter"
      },
      {
        "rekkefoelge": 10,
        "tilhoerer-hovedomraade": null,
        "kode": "K8105",
        "uri": "http://psi.udir.no/kl06/K8105",
        "url-data": "http://data.udir.no/kl06/K8105",
        "tittel": "følge bruksanvisning og bruke manual for utstyr som benyttes i produksjonen"
      },
      {
        "rekkefoelge": 11,
        "tilhoerer-hovedomraade": null,
        "kode": "K8106",
        "uri": "http://psi.udir.no/kl06/K8106",
        "url-data": "http://data.udir.no/kl06/K8106",
        "tittel": "velge og bruke materialer ut fra arbeidsoppdrag og materialets egenskaper"
      },
      {
        "rekkefoelge": 12,
        "tilhoerer-hovedomraade": null,
        "kode": "K8107",
        "uri": "http://psi.udir.no/kl06/K8107",
        "url-data": "http://data.udir.no/kl06/K8107",
        "tittel": "utføre enkelt vedlikehold på bygninger og installasjoner som benyttes i produksjonen"
      },
      {
        "rekkefoelge": 13,
        "tilhoerer-hovedomraade": null,
        "kode": "K8108",
        "uri": "http://psi.udir.no/kl06/K8108",
        "url-data": "http://data.udir.no/kl06/K8108",
        "tittel": "planlegge og gjennomføre arbeid og aktiviteter i tråd med gjeldende yrkesmessige krav til utførelse, helse, miljø og sikkerhet og kvalitetssystemer"
      },
      {
        "rekkefoelge": 14,
        "tilhoerer-hovedomraade": null,
        "kode": "K8109",
        "uri": "http://psi.udir.no/kl06/K8109",
        "url-data": "http://data.udir.no/kl06/K8109",
        "tittel": "bruke riktig arbeidsteknikk, verne- og sikkerhetsutstyr og velge hensiktsmessig påkledning for arbeid og aktiviteter under ulike forhold"
      },
      {
        "rekkefoelge": 15,
        "tilhoerer-hovedomraade": null,
        "kode": "K8110",
        "uri": "http://psi.udir.no/kl06/K8110",
        "url-data": "http://data.udir.no/kl06/K8110",
        "tittel": "utøve brannvern og førstehjelp i tråd med gjeldende krav"
      },
      {
        "rekkefoelge": 16,
        "tilhoerer-hovedomraade": null,
        "kode": "K8111",
        "uri": "http://psi.udir.no/kl06/K8111",
        "url-data": "http://data.udir.no/kl06/K8111",
        "tittel": "dokumentere gjennomført opplæring i forhold til IMO 60 (gjelder kun for elever som har fiske og fangst som en av produksjonene)"
      }
    ]
  },
  {
    "id": "NANAB1----",
    "name": "Naturbruk",
    "programUrl": "https://www.udir.no/kl06/NANAB1----",
    "lareplanUrl": "https://data.udir.no/kl06/NAB1-01",
    "kompetansemaal": [
      {
        "rekkefoelge": 1,
        "tilhoerer-hovedomraade": null,
        "kode": "K8096",
        "uri": "http://psi.udir.no/kl06/K8096",
        "url-data": "http://data.udir.no/kl06/K8096",
        "tittel": "utføre arbeidsoppgaver knyttet til stell av planter basert på kunnskaper om planters miljøkrav"
      },
      {
        "rekkefoelge": 2,
        "tilhoerer-hovedomraade": null,
        "kode": "K8097",
        "uri": "http://psi.udir.no/kl06/K8097",
        "url-data": "http://data.udir.no/kl06/K8097",
        "tittel": "utføre arbeidsoppgaver knyttet til stell av dyr eller fisk basert på etiske retningslinjer og kunnskaper om organismenes miljøkrav"
      },
      {
        "rekkefoelge": 3,
        "tilhoerer-hovedomraade": null,
        "kode": "K8098",
        "uri": "http://psi.udir.no/kl06/K8098",
        "url-data": "http://data.udir.no/kl06/K8098",
        "tittel": "utføre arbeidsoppgaver innen produksjon og høsting eller fangst"
      },
      {
        "rekkefoelge": 4,
        "tilhoerer-hovedomraade": null,
        "kode": "K8099",
        "uri": "http://psi.udir.no/kl06/K8099",
        "url-data": "http://data.udir.no/kl06/K8099",
        "tittel": "utføre enkel bearbeiding av råstoff"
      },
      {
        "rekkefoelge": 5,
        "tilhoerer-hovedomraade": null,
        "kode": "K8100",
        "uri": "http://psi.udir.no/kl06/K8100",
        "url-data": "http://data.udir.no/kl06/K8100",
        "tittel": "beskrive og presentere et produkt rettet mot en aktuell målgruppe"
      },
      {
        "rekkefoelge": 6,
        "tilhoerer-hovedomraade": null,
        "kode": "K8101",
        "uri": "http://psi.udir.no/kl06/K8101",
        "url-data": "http://data.udir.no/kl06/K8101",
        "tittel": "identifisere, klassifisere og presentere et utvalg arter og materialer"
      },
      {
        "rekkefoelge": 7,
        "tilhoerer-hovedomraade": null,
        "kode": "K8102",
        "uri": "http://psi.udir.no/kl06/K8102",
        "url-data": "http://data.udir.no/kl06/K8102",
        "tittel": "foreta enkle beregninger av råvare- og materialforbruk, og kunne beregne utbyttet i produksjonsprosessen"
      },
      {
        "rekkefoelge": 8,
        "tilhoerer-hovedomraade": null,
        "kode": "K8103",
        "uri": "http://psi.udir.no/kl06/K8103",
        "url-data": "http://data.udir.no/kl06/K8103",
        "tittel": "velge og bruke riktig redskap, utstyr og instrumenter i tilknytning til produksjonen"
      },
      {
        "rekkefoelge": 9,
        "tilhoerer-hovedomraade": null,
        "kode": "K8104",
        "uri": "http://psi.udir.no/kl06/K8104",
        "url-data": "http://data.udir.no/kl06/K8104",
        "tittel": "foreta enkelt ettersyn av aktuelle framkomstmidler, motorer, redskaper, utstyr og instrumenter"
      },
      {
        "rekkefoelge": 10,
        "tilhoerer-hovedomraade": null,
        "kode": "K8105",
        "uri": "http://psi.udir.no/kl06/K8105",
        "url-data": "http://data.udir.no/kl06/K8105",
        "tittel": "følge bruksanvisning og bruke manual for utstyr som benyttes i produksjonen"
      },
      {
        "rekkefoelge": 11,
        "tilhoerer-hovedomraade": null,
        "kode": "K8106",
        "uri": "http://psi.udir.no/kl06/K8106",
        "url-data": "http://data.udir.no/kl06/K8106",
        "tittel": "velge og bruke materialer ut fra arbeidsoppdrag og materialets egenskaper"
      },
      {
        "rekkefoelge": 12,
        "tilhoerer-hovedomraade": null,
        "kode": "K8107",
        "uri": "http://psi.udir.no/kl06/K8107",
        "url-data": "http://data.udir.no/kl06/K8107",
        "tittel": "utføre enkelt vedlikehold på bygninger og installasjoner som benyttes i produksjonen"
      },
      {
        "rekkefoelge": 13,
        "tilhoerer-hovedomraade": null,
        "kode": "K8108",
        "uri": "http://psi.udir.no/kl06/K8108",
        "url-data": "http://data.udir.no/kl06/K8108",
        "tittel": "planlegge og gjennomføre arbeid og aktiviteter i tråd med gjeldende yrkesmessige krav til utførelse, helse, miljø og sikkerhet og kvalitetssystemer"
      },
      {
        "rekkefoelge": 14,
        "tilhoerer-hovedomraade": null,
        "kode": "K8109",
        "uri": "http://psi.udir.no/kl06/K8109",
        "url-data": "http://data.udir.no/kl06/K8109",
        "tittel": "bruke riktig arbeidsteknikk, verne- og sikkerhetsutstyr og velge hensiktsmessig påkledning for arbeid og aktiviteter under ulike forhold"
      },
      {
        "rekkefoelge": 15,
        "tilhoerer-hovedomraade": null,
        "kode": "K8110",
        "uri": "http://psi.udir.no/kl06/K8110",
        "url-data": "http://data.udir.no/kl06/K8110",
        "tittel": "utøve brannvern og førstehjelp i tråd med gjeldende krav"
      },
      {
        "rekkefoelge": 16,
        "tilhoerer-hovedomraade": null,
        "kode": "K8111",
        "uri": "http://psi.udir.no/kl06/K8111",
        "url-data": "http://data.udir.no/kl06/K8111",
        "tittel": "dokumentere gjennomført opplæring i forhold til IMO 60 (gjelder kun for elever som har fiske og fangst som en av produksjonene)"
      }
    ]
  },
  {
    "id": "NANAB1----",
    "name": "Naturbruk",
    "programUrl": "https://www.udir.no/kl06/NANAB1----",
    "lareplanUrl": "https://data.udir.no/kl06/NAB1-01",
    "kompetansemaal": [
      {
        "rekkefoelge": 1,
        "tilhoerer-hovedomraade": null,
        "kode": "K8096",
        "uri": "http://psi.udir.no/kl06/K8096",
        "url-data": "http://data.udir.no/kl06/K8096",
        "tittel": "utføre arbeidsoppgaver knyttet til stell av planter basert på kunnskaper om planters miljøkrav"
      },
      {
        "rekkefoelge": 2,
        "tilhoerer-hovedomraade": null,
        "kode": "K8097",
        "uri": "http://psi.udir.no/kl06/K8097",
        "url-data": "http://data.udir.no/kl06/K8097",
        "tittel": "utføre arbeidsoppgaver knyttet til stell av dyr eller fisk basert på etiske retningslinjer og kunnskaper om organismenes miljøkrav"
      },
      {
        "rekkefoelge": 3,
        "tilhoerer-hovedomraade": null,
        "kode": "K8098",
        "uri": "http://psi.udir.no/kl06/K8098",
        "url-data": "http://data.udir.no/kl06/K8098",
        "tittel": "utføre arbeidsoppgaver innen produksjon og høsting eller fangst"
      },
      {
        "rekkefoelge": 4,
        "tilhoerer-hovedomraade": null,
        "kode": "K8099",
        "uri": "http://psi.udir.no/kl06/K8099",
        "url-data": "http://data.udir.no/kl06/K8099",
        "tittel": "utføre enkel bearbeiding av råstoff"
      },
      {
        "rekkefoelge": 5,
        "tilhoerer-hovedomraade": null,
        "kode": "K8100",
        "uri": "http://psi.udir.no/kl06/K8100",
        "url-data": "http://data.udir.no/kl06/K8100",
        "tittel": "beskrive og presentere et produkt rettet mot en aktuell målgruppe"
      },
      {
        "rekkefoelge": 6,
        "tilhoerer-hovedomraade": null,
        "kode": "K8101",
        "uri": "http://psi.udir.no/kl06/K8101",
        "url-data": "http://data.udir.no/kl06/K8101",
        "tittel": "identifisere, klassifisere og presentere et utvalg arter og materialer"
      },
      {
        "rekkefoelge": 7,
        "tilhoerer-hovedomraade": null,
        "kode": "K8102",
        "uri": "http://psi.udir.no/kl06/K8102",
        "url-data": "http://data.udir.no/kl06/K8102",
        "tittel": "foreta enkle beregninger av råvare- og materialforbruk, og kunne beregne utbyttet i produksjonsprosessen"
      },
      {
        "rekkefoelge": 8,
        "tilhoerer-hovedomraade": null,
        "kode": "K8103",
        "uri": "http://psi.udir.no/kl06/K8103",
        "url-data": "http://data.udir.no/kl06/K8103",
        "tittel": "velge og bruke riktig redskap, utstyr og instrumenter i tilknytning til produksjonen"
      },
      {
        "rekkefoelge": 9,
        "tilhoerer-hovedomraade": null,
        "kode": "K8104",
        "uri": "http://psi.udir.no/kl06/K8104",
        "url-data": "http://data.udir.no/kl06/K8104",
        "tittel": "foreta enkelt ettersyn av aktuelle framkomstmidler, motorer, redskaper, utstyr og instrumenter"
      },
      {
        "rekkefoelge": 10,
        "tilhoerer-hovedomraade": null,
        "kode": "K8105",
        "uri": "http://psi.udir.no/kl06/K8105",
        "url-data": "http://data.udir.no/kl06/K8105",
        "tittel": "følge bruksanvisning og bruke manual for utstyr som benyttes i produksjonen"
      },
      {
        "rekkefoelge": 11,
        "tilhoerer-hovedomraade": null,
        "kode": "K8106",
        "uri": "http://psi.udir.no/kl06/K8106",
        "url-data": "http://data.udir.no/kl06/K8106",
        "tittel": "velge og bruke materialer ut fra arbeidsoppdrag og materialets egenskaper"
      },
      {
        "rekkefoelge": 12,
        "tilhoerer-hovedomraade": null,
        "kode": "K8107",
        "uri": "http://psi.udir.no/kl06/K8107",
        "url-data": "http://data.udir.no/kl06/K8107",
        "tittel": "utføre enkelt vedlikehold på bygninger og installasjoner som benyttes i produksjonen"
      },
      {
        "rekkefoelge": 13,
        "tilhoerer-hovedomraade": null,
        "kode": "K8108",
        "uri": "http://psi.udir.no/kl06/K8108",
        "url-data": "http://data.udir.no/kl06/K8108",
        "tittel": "planlegge og gjennomføre arbeid og aktiviteter i tråd med gjeldende yrkesmessige krav til utførelse, helse, miljø og sikkerhet og kvalitetssystemer"
      },
      {
        "rekkefoelge": 14,
        "tilhoerer-hovedomraade": null,
        "kode": "K8109",
        "uri": "http://psi.udir.no/kl06/K8109",
        "url-data": "http://data.udir.no/kl06/K8109",
        "tittel": "bruke riktig arbeidsteknikk, verne- og sikkerhetsutstyr og velge hensiktsmessig påkledning for arbeid og aktiviteter under ulike forhold"
      },
      {
        "rekkefoelge": 15,
        "tilhoerer-hovedomraade": null,
        "kode": "K8110",
        "uri": "http://psi.udir.no/kl06/K8110",
        "url-data": "http://data.udir.no/kl06/K8110",
        "tittel": "utøve brannvern og førstehjelp i tråd med gjeldende krav"
      },
      {
        "rekkefoelge": 16,
        "tilhoerer-hovedomraade": null,
        "kode": "K8111",
        "uri": "http://psi.udir.no/kl06/K8111",
        "url-data": "http://data.udir.no/kl06/K8111",
        "tittel": "dokumentere gjennomført opplæring i forhold til IMO 60 (gjelder kun for elever som har fiske og fangst som en av produksjonene)"
      }
    ]
  },
  {
    "id": "NANAB1----",
    "name": "Naturbruk",
    "programUrl": "https://www.udir.no/kl06/NANAB1----",
    "lareplanUrl": "https://data.udir.no/kl06/NAB1-01",
    "kompetansemaal": [
      {
        "rekkefoelge": 1,
        "tilhoerer-hovedomraade": null,
        "kode": "K8096",
        "uri": "http://psi.udir.no/kl06/K8096",
        "url-data": "http://data.udir.no/kl06/K8096",
        "tittel": "utføre arbeidsoppgaver knyttet til stell av planter basert på kunnskaper om planters miljøkrav"
      },
      {
        "rekkefoelge": 2,
        "tilhoerer-hovedomraade": null,
        "kode": "K8097",
        "uri": "http://psi.udir.no/kl06/K8097",
        "url-data": "http://data.udir.no/kl06/K8097",
        "tittel": "utføre arbeidsoppgaver knyttet til stell av dyr eller fisk basert på etiske retningslinjer og kunnskaper om organismenes miljøkrav"
      },
      {
        "rekkefoelge": 3,
        "tilhoerer-hovedomraade": null,
        "kode": "K8098",
        "uri": "http://psi.udir.no/kl06/K8098",
        "url-data": "http://data.udir.no/kl06/K8098",
        "tittel": "utføre arbeidsoppgaver innen produksjon og høsting eller fangst"
      },
      {
        "rekkefoelge": 4,
        "tilhoerer-hovedomraade": null,
        "kode": "K8099",
        "uri": "http://psi.udir.no/kl06/K8099",
        "url-data": "http://data.udir.no/kl06/K8099",
        "tittel": "utføre enkel bearbeiding av råstoff"
      },
      {
        "rekkefoelge": 5,
        "tilhoerer-hovedomraade": null,
        "kode": "K8100",
        "uri": "http://psi.udir.no/kl06/K8100",
        "url-data": "http://data.udir.no/kl06/K8100",
        "tittel": "beskrive og presentere et produkt rettet mot en aktuell målgruppe"
      },
      {
        "rekkefoelge": 6,
        "tilhoerer-hovedomraade": null,
        "kode": "K8101",
        "uri": "http://psi.udir.no/kl06/K8101",
        "url-data": "http://data.udir.no/kl06/K8101",
        "tittel": "identifisere, klassifisere og presentere et utvalg arter og materialer"
      },
      {
        "rekkefoelge": 7,
        "tilhoerer-hovedomraade": null,
        "kode": "K8102",
        "uri": "http://psi.udir.no/kl06/K8102",
        "url-data": "http://data.udir.no/kl06/K8102",
        "tittel": "foreta enkle beregninger av råvare- og materialforbruk, og kunne beregne utbyttet i produksjonsprosessen"
      },
      {
        "rekkefoelge": 8,
        "tilhoerer-hovedomraade": null,
        "kode": "K8103",
        "uri": "http://psi.udir.no/kl06/K8103",
        "url-data": "http://data.udir.no/kl06/K8103",
        "tittel": "velge og bruke riktig redskap, utstyr og instrumenter i tilknytning til produksjonen"
      },
      {
        "rekkefoelge": 9,
        "tilhoerer-hovedomraade": null,
        "kode": "K8104",
        "uri": "http://psi.udir.no/kl06/K8104",
        "url-data": "http://data.udir.no/kl06/K8104",
        "tittel": "foreta enkelt ettersyn av aktuelle framkomstmidler, motorer, redskaper, utstyr og instrumenter"
      },
      {
        "rekkefoelge": 10,
        "tilhoerer-hovedomraade": null,
        "kode": "K8105",
        "uri": "http://psi.udir.no/kl06/K8105",
        "url-data": "http://data.udir.no/kl06/K8105",
        "tittel": "følge bruksanvisning og bruke manual for utstyr som benyttes i produksjonen"
      },
      {
        "rekkefoelge": 11,
        "tilhoerer-hovedomraade": null,
        "kode": "K8106",
        "uri": "http://psi.udir.no/kl06/K8106",
        "url-data": "http://data.udir.no/kl06/K8106",
        "tittel": "velge og bruke materialer ut fra arbeidsoppdrag og materialets egenskaper"
      },
      {
        "rekkefoelge": 12,
        "tilhoerer-hovedomraade": null,
        "kode": "K8107",
        "uri": "http://psi.udir.no/kl06/K8107",
        "url-data": "http://data.udir.no/kl06/K8107",
        "tittel": "utføre enkelt vedlikehold på bygninger og installasjoner som benyttes i produksjonen"
      },
      {
        "rekkefoelge": 13,
        "tilhoerer-hovedomraade": null,
        "kode": "K8108",
        "uri": "http://psi.udir.no/kl06/K8108",
        "url-data": "http://data.udir.no/kl06/K8108",
        "tittel": "planlegge og gjennomføre arbeid og aktiviteter i tråd med gjeldende yrkesmessige krav til utførelse, helse, miljø og sikkerhet og kvalitetssystemer"
      },
      {
        "rekkefoelge": 14,
        "tilhoerer-hovedomraade": null,
        "kode": "K8109",
        "uri": "http://psi.udir.no/kl06/K8109",
        "url-data": "http://data.udir.no/kl06/K8109",
        "tittel": "bruke riktig arbeidsteknikk, verne- og sikkerhetsutstyr og velge hensiktsmessig påkledning for arbeid og aktiviteter under ulike forhold"
      },
      {
        "rekkefoelge": 15,
        "tilhoerer-hovedomraade": null,
        "kode": "K8110",
        "uri": "http://psi.udir.no/kl06/K8110",
        "url-data": "http://data.udir.no/kl06/K8110",
        "tittel": "utøve brannvern og førstehjelp i tråd med gjeldende krav"
      },
      {
        "rekkefoelge": 16,
        "tilhoerer-hovedomraade": null,
        "kode": "K8111",
        "uri": "http://psi.udir.no/kl06/K8111",
        "url-data": "http://data.udir.no/kl06/K8111",
        "tittel": "dokumentere gjennomført opplæring i forhold til IMO 60 (gjelder kun for elever som har fiske og fangst som en av produksjonene)"
      }
    ]
  }
]